{
    "spawns": [
        {
            "team": 0,
            "origin": [
                798,
                -1715,
                115
            ],
            "angle": [
                16,
                -86
            ],
            "vAngle": [
                -5,
                -86
            ]
        },
        {
            "team": 0,
            "origin": [
                -389,
                -1696,
                115
            ],
            "angle": [
                9,
                -177
            ],
            "vAngle": [
                -3,
                -177
            ]
        },
        {
            "team": 0,
            "origin": [
                1482,
                130,
                120
            ],
            "angle": [
                24,
                178
            ],
            "vAngle": [
                -8,
                178
            ]
        },
        {
            "team": 0,
            "origin": [
                550,
                242,
                115
            ],
            "angle": [
                14,
                178
            ],
            "vAngle": [
                -5,
                178
            ]
        },
        {
            "team": 0,
            "origin": [
                -455,
                270,
                51
            ],
            "angle": [
                6,
                -177
            ],
            "vAngle": [
                -2,
                -177
            ]
        },
        {
            "team": 0,
            "origin": [
                -318,
                -732,
                68
            ],
            "angle": [
                12,
                1
            ],
            "vAngle": [
                -4,
                1
            ]
        },
        {
            "team": 0,
            "origin": [
                -1542,
                213,
                83
            ],
            "angle": [
                4,
                90
            ],
            "vAngle": [
                -1,
                90
            ]
        },
        {
            "team": 0,
            "origin": [
                1072,
                826,
                51
            ],
            "angle": [
                5,
                -91
            ],
            "vAngle": [
                -2,
                -91
            ]
        },
        {
            "team": 0,
            "origin": [
                2372,
                852,
                51
            ],
            "angle": [
                6,
                -179
            ],
            "vAngle": [
                -2,
                -179
            ]
        },
        {
            "team": 0,
            "origin": [
                1515,
                1399,
                51
            ],
            "angle": [
                6,
                -59
            ],
            "vAngle": [
                -2,
                -59
            ]
        },
        {
            "team": 0,
            "origin": [
                801,
                1807,
                83
            ],
            "angle": [
                10,
                88
            ],
            "vAngle": [
                -3,
                88
            ]
        },
        {
            "team": 0,
            "origin": [
                946,
                3233,
                51
            ],
            "angle": [
                6,
                -90
            ],
            "vAngle": [
                -2,
                -90
            ]
        },
        {
            "team": 0,
            "origin": [
                194,
                3517,
                51
            ],
            "angle": [
                9,
                -179
            ],
            "vAngle": [
                -3,
                -179
            ]
        },
        {
            "team": 0,
            "origin": [
                -502,
                3628,
                62
            ],
            "angle": [
                9,
                -89
            ],
            "vAngle": [
                -3,
                -89
            ]
        },
        {
            "team": 0,
            "origin": [
                -1353,
                3630,
                51
            ],
            "angle": [
                9,
                -86
            ],
            "vAngle": [
                -3,
                -86
            ]
        },
        {
            "team": 0,
            "origin": [
                -1610,
                2868,
                83
            ],
            "angle": [
                10,
                -90
            ],
            "vAngle": [
                -3,
                -90
            ]
        },
        {
            "team": 0,
            "origin": [
                -537,
                2094,
                51
            ],
            "angle": [
                12,
                93
            ],
            "vAngle": [
                -4,
                93
            ]
        },
        {
            "team": 0,
            "origin": [
                -1001,
                1489,
                51
            ],
            "angle": [
                8,
                -89
            ],
            "vAngle": [
                -3,
                -89
            ]
        },
        {
            "team": 0,
            "origin": [
                -819,
                1145,
                -140
            ],
            "angle": [
                9,
                -180
            ],
            "vAngle": [
                -3,
                -180
            ]
        },
        {
            "team": 0,
            "origin": [
                -1106,
                1979,
                -140
            ],
            "angle": [
                2,
                3
            ],
            "vAngle": [
                -1,
                3
            ]
        },
        {
            "team": 0,
            "origin": [
                -201,
                1552,
                83
            ],
            "angle": [
                4,
                -1
            ],
            "vAngle": [
                -1,
                -1
            ]
        },
        {
            "team": 0,
            "origin": [
                654,
                1293,
                83
            ],
            "angle": [
                7,
                -91
            ],
            "vAngle": [
                -2,
                -91
            ]
        },
        {
            "team": 0,
            "origin": [
                210,
                837,
                51
            ],
            "angle": [
                7,
                -92
            ],
            "vAngle": [
                -2,
                -92
            ]
        },
        {
            "team": 0,
            "origin": [
                -1100,
                1189,
                -12
            ],
            "angle": [
                18,
                -3
            ],
            "vAngle": [
                -6,
                -3
            ]
        },
        {
            "team": 0,
            "origin": [
                -1626,
                2109,
                83
            ],
            "angle": [
                7,
                -1
            ],
            "vAngle": [
                -2,
                -1
            ]
        },
        {
            "team": 0,
            "origin": [
                1369,
                -1002,
                115
            ],
            "angle": [
                9,
                88
            ],
            "vAngle": [
                -3,
                88
            ]
        },
        {
            "team": 0,
            "origin": [
                431,
                -59,
                51
            ],
            "angle": [
                7,
                -97
            ],
            "vAngle": [
                -2,
                -97
            ]
        },
        {
            "team": 0,
            "origin": [
                -70,
                1842,
                83
            ],
            "angle": [
                7,
                1
            ],
            "vAngle": [
                -2,
                1
            ]
        },
        {
            "team": 0,
            "origin": [
                -1527,
                1634,
                83
            ],
            "angle": [
                4,
                91
            ],
            "vAngle": [
                -1,
                91
            ]
        },
        {
            "team": 0,
            "origin": [
                -820,
                468,
                83
            ],
            "angle": [
                10,
                95
            ],
            "vAngle": [
                -3,
                95
            ]
        },
        {
            "team": 0,
            "origin": [
                862,
                1502,
                -140
            ],
            "angle": [
                10,
                -137
            ],
            "vAngle": [
                -3,
                -137
            ]
        },
        {
            "team": 0,
            "origin": [
                2373,
                476,
                59
            ],
            "angle": [
                7,
                88
            ],
            "vAngle": [
                -2,
                88
            ]
        },
        {
            "team": 0,
            "origin": [
                -633,
                -728,
                51
            ],
            "angle": [
                8,
                -2
            ],
            "vAngle": [
                -3,
                -2
            ]
        }
    ]
}